CHANGES.rst
MANIFEST.in
README.rst
setup.cfg
setup.py
bigmax/__init__.py
bigmax/exceptions.py
bigmax/resources.py
bigmax/utils.py
bigmax.egg-info/PKG-INFO
bigmax.egg-info/SOURCES.txt
bigmax.egg-info/dependency_links.txt
bigmax.egg-info/entry_points.txt
bigmax.egg-info/not-zip-safe
bigmax.egg-info/requires.txt
bigmax.egg-info/top_level.txt
bigmax/.compass/config.rb
bigmax/bootstrap/css/bootstrap-theme.css
bigmax/bootstrap/css/bootstrap-theme.min.css
bigmax/bootstrap/css/bootstrap.css
bigmax/bootstrap/css/bootstrap.min.css
bigmax/bootstrap/fonts/glyphicons-halflings-regular.eot
bigmax/bootstrap/fonts/glyphicons-halflings-regular.svg
bigmax/bootstrap/fonts/glyphicons-halflings-regular.ttf
bigmax/bootstrap/fonts/glyphicons-halflings-regular.woff
bigmax/bootstrap/js/bootstrap.js
bigmax/bootstrap/js/bootstrap.min.js
bigmax/js/explorer.js
bigmax/js/main.js
bigmax/js/plugins.js
bigmax/js/deprecated/maxclient.js
bigmax/js/deprecated/script.js
bigmax/js/libs/jquery-1.9.1.min.js
bigmax/js/libs/modernizr-2.6.2.min.js
bigmax/less/bigmax.less
bigmax/maxui/maxui.css
bigmax/maxui/maxui.js
bigmax/maxui/maxui.loader.js
bigmax/maxui/seturls.sh
bigmax/maxui/img/bgact.gif
bigmax/maxui/img/conversations.png
bigmax/maxui/img/maxcomm.png
bigmax/maxui/img/maxcomm@2x.png
bigmax/maxui/img/timeline.png
bigmax/maxui/img/to_conversation.png
bigmax/maxui/img/transparent.gif
bigmax/maxui/img/trashbin.png
bigmax/maxui/img/trashbino.png
bigmax/maxui/img/x.png
bigmax/scss/_max.scss
bigmax/scss/style.scss
bigmax/static/404.html
bigmax/static/PoweredMongoDBbeige50.png
bigmax/static/PoweredMongoDBblue50.png
bigmax/static/apple-touch-icon-114x114-precomposed.png
bigmax/static/apple-touch-icon-57x57-precomposed.png
bigmax/static/apple-touch-icon-72x72-precomposed.png
bigmax/static/apple-touch-icon-precomposed.png
bigmax/static/apple-touch-icon.png
bigmax/static/favicon.ico
bigmax/static/gillsansbold.ttf
bigmax/static/glyphicons-halflings-white.png
bigmax/static/glyphicons-halflings.png
bigmax/static/humans.txt
bigmax/static/index.html
bigmax/static/logo_MAX_blanc.png
bigmax/static/logo_MAX_color.png
bigmax/static/logo_MAX_gris.png
bigmax/static/pyramid-small.png
bigmax/static/pyramid.png
