Metadata-Version: 1.1
Name: bigmax
Version: 3.5.1
Summary: Big MAX - MAX Web Administration Interface
Home-page: http://github.com/upcnet/bigmax
Author: UPCnet Content Management Team
Author-email: victor.fernandez@upcnet.es
License: UNKNOWN
Keywords: web pylons pyramid mongodb
Platform: UNKNOWN
Classifier: Programming Language :: Python
Classifier: Framework :: Pylons
Classifier: Topic :: Internet :: WWW/HTTP
Classifier: Topic :: Internet :: WWW/HTTP :: WSGI :: Application
